custom_aoai_gpt4mm/__init__.py
custom_aoai_gpt4mm/tools/__init__.py
custom_aoai_gpt4mm/tools/custom_aoai_gpt4mm.py
custom_aoai_gpt4mm/tools/utils.py
custom_aoai_gpt4mm/yamls/custom_aoai_gpt4mm.yaml
tests/__init__.py
tests/test_custom_aoai_gpt4mm.py
tests/utils.py
custom_aoai_gpt4mm-0.0.5.dist-info/LICENSE.txt
custom_aoai_gpt4mm-0.0.5.dist-info/METADATA
custom_aoai_gpt4mm-0.0.5.dist-info/WHEEL
custom_aoai_gpt4mm-0.0.5.dist-info/entry_points.txt
custom_aoai_gpt4mm-0.0.5.dist-info/top_level.txt
custom_aoai_gpt4mm-0.0.5.dist-info/RECORD
